COPYING
MANIFEST.in
README.rst
setup.py
django_switch_templatetag.egg-info/PKG-INFO
django_switch_templatetag.egg-info/SOURCES.txt
django_switch_templatetag.egg-info/dependency_links.txt
django_switch_templatetag.egg-info/requires.txt
django_switch_templatetag.egg-info/top_level.txt
switch_templatetag/__init__.py
switch_templatetag/models.py
switch_templatetag/templatetags/__init__.py
switch_templatetag/templatetags/switch.py