Metadata-Version: 1.0
Name: django-switch-templatetag
Version: 2.0.4
Summary: Simple switch tag for Django templates.
Home-page: https://chris-lamb.co.uk/projects/django-switch-templatetag
Author: Chris Lamb
Author-email: chris@chris-lamb.co.uk
License: BSD
Platform: UNKNOWN
